diffcoverage/__init__.py
diffcoverage/all_coverage.py
diffcoverage/diff_coverage.py
diffcoverage/patch.py
diffcoverage/settings.py
diffcoverage/templates/cobertura/layout.html
diffcoverage/templates/cobertura/row.html
diffcoverage-1.0.3.dist-info/DESCRIPTION.rst
diffcoverage-1.0.3.dist-info/entry_points.txt
diffcoverage-1.0.3.dist-info/METADATA
diffcoverage-1.0.3.dist-info/metadata.json
diffcoverage-1.0.3.dist-info/RECORD
diffcoverage-1.0.3.dist-info/top_level.txt
diffcoverage-1.0.3.dist-info/WHEEL
