Metadata-Version: 2.0
Name: diffcoverage
Version: 1.0.3
Summary: Measure difference in coverage with a difference patch
Home-page: https://github.com/gxx/diff-coverage
Author: Andrew Crosio
Author-email: andrew@andrewcrosio.com
License: Unlicensed
Platform: any
Classifier: Topic :: Internet
Classifier: Natural Language :: English
Classifier: Intended Audience :: Developers
Classifier: License :: Freely Distributable
Classifier: Programming Language :: Python :: 2.6
Classifier: Programming Language :: Python :: 2.7
Requires-Dist: coverage (>=3.7)
